{
    "1005": {
        "location": "1005",
        "parent": "root",
        "volume": 1386061
    },
    "100510": {
        "location": "100510",
        "parent": "1005",
        "volume": 1354408
    },
    "10051000": {
        "location": "10051000",
        "parent": "100510",
        "volume": 1354408
    },
    "100590": {
        "location": "100590",
        "parent": "1005",
        "volume": 31653
    },
    "10059010": {
        "location": "10059010",
        "parent": "100590",
        "volume": 1529
    },
    "10059090": {
        "location": "10059090",
        "parent": "100590",
        "volume": 30124
    },
    "1006": {
        "location": "1006",
        "parent": "root",
        "volume": 85601962
    },
    "100610": {
        "location": "100610",
        "parent": "1006",
        "volume": 1
    },
    "10061090": {
        "location": "10061090",
        "parent": "100610",
        "volume": 1
    },
    "100620": {
        "location": "100620",
        "parent": "1006",
        "volume": 3044413
    },
    "10062010": {
        "location": "10062010",
        "parent": "100620",
        "volume": 299043
    },
    "10062090": {
        "location": "10062090",
        "parent": "100620",
        "volume": 2745370
    },
    "100630": {
        "location": "100630",
        "parent": "1006",
        "volume": 76719432
    },
    "10063030": {
        "location": "10063030",
        "parent": "100630",
        "volume": 1042235
    },
    "10063040": {
        "location": "10063040",
        "parent": "100630",
        "volume": 24807708
    },
    "10063091": {
        "location": "10063091",
        "parent": "100630",
        "volume": 4547738
    },
    "10063099": {
        "location": "10063099",
        "parent": "100630",
        "volume": 46321751
    },
    "100640": {
        "location": "100640",
        "parent": "1006",
        "volume": 5838116
    },
    "10064090": {
        "location": "10064090",
        "parent": "100640",
        "volume": 5838116
    },
    "1511": {
        "location": "1511",
        "parent": "root",
        "volume": 830078
    },
    "151190": {
        "location": "151190",
        "parent": "1511",
        "volume": 830078
    },
    "15119020": {
        "location": "15119020",
        "parent": "151190",
        "volume": 4112
    },
    "15119032": {
        "location": "15119032",
        "parent": "151190",
        "volume": 191
    },
    "15119036": {
        "location": "15119036",
        "parent": "151190",
        "volume": 800050
    },
    "15119039": {
        "location": "15119039",
        "parent": "151190",
        "volume": 24513
    },
    "15119049": {
        "location": "15119049",
        "parent": "151190",
        "volume": 1212
    },
    "root": {
        "location": "root",
        "parent": null,
        "volume": 87818101
    }
}